near_api/__init__.py
near_api/account.py
near_api/providers.py
near_api/serializer.py
near_api/signer.py
near_api/transactions.py
nobi_near_api-1.0.1.dist-info/LICENSE
nobi_near_api-1.0.1.dist-info/LICENSE-APACHE
nobi_near_api-1.0.1.dist-info/METADATA
nobi_near_api-1.0.1.dist-info/WHEEL
nobi_near_api-1.0.1.dist-info/top_level.txt
nobi_near_api-1.0.1.dist-info/RECORD
