Metadata-Version: 2.1
Name: nobi-near-api
Version: 1.0.1
Home-page: https://github.com/nobbennob/nobi-near-api
Author: NEAR Inc
License: MIT
License-File: LICENSE
License-File: LICENSE-APACHE
Requires-Dist: requests
Requires-Dist: base58
Requires-Dist: ed25519
